Metadata-Version: 1.0
Name: np-distributions
Version: 1.0
Summary: Gaussian and binomial distributions
Home-page: UNKNOWN
Author: Nadine Puetzer
Author-email: nadine.puetzer@freenet.de
License: UNKNOWN
Platform: UNKNOWN
